README.md
setup.cfg
setup.py
lru/__init__.py
py3_lru_cache.egg-info/PKG-INFO
py3_lru_cache.egg-info/SOURCES.txt
py3_lru_cache.egg-info/dependency_links.txt
py3_lru_cache.egg-info/top_level.txt