Metadata-Version: 1.0
Name: py3-lru-cache
Version: 0.1.5
Summary: LRU cache for python. Provides a dictionary-like object as well as a method decorator. A fork of Chris Stucchio's py_lru_cache
Home-page: https://github.com/amock/Python-LRU-cache
Author: Alan Mock
Author-email: pypi.org@alanmock.com
License: Dual: GPL v3 or BSD
Platform: UNKNOWN
